README.txt
setup.py
count_min_sketch/__init__.py
count_min_sketch/count_min_sketch.py
count_min_sketch/speed_test.py
count_min_sketch.egg-info/PKG-INFO
count_min_sketch.egg-info/SOURCES.txt
count_min_sketch.egg-info/dependency_links.txt
count_min_sketch.egg-info/top_level.txt