Metadata-Version: 1.1
Name: count-min-sketch
Version: 1.0.1
Summary: A fast Count-Min Sketch data structure.
Home-page: https://github.com/AWNystrom/CountMinSketch
Author: Andrew Nystrom
Author-email: AWNystrom@gmail.com
License: Apache 2.0
Keywords: count,min,sketch,fast
Platform: UNKNOWN
Classifier: Programming Language :: Python
Classifier: Programming Language :: Python :: 2.7
Classifier: Programming Language :: Python :: 2
Classifier: License :: OSI Approved :: Apache Software License
Classifier: Operating System :: OS Independent
Classifier: Development Status :: 4 - Beta
Classifier: Intended Audience :: Developers
